{"state":"trained","evaluationState":"evaluated","version":"1.0","modifiedDate":"2024-08-30T13:08:35Z","evaluationEntity":{"dataResult":{},"analysedDataType":"none","id":"69c76122-5f43-4719-bdee-ed124575943c"},"preferredFilename":"EmotionsImageClassifier 3","title":"EmotionsImageClassifier 3","snapshotRole":{"withoutSnapshots":0},"activityEntities":["trainingStarted",[{"createdDate":"2024-08-30T12:50:06Z","id":"34AD7D25-94ED-4211-8D33-0D87655652B2","subtitle":"25 iterations","title":"Training Started","event":"trainingStarted"}],"trainingFinished",[{"event":"trainingFinished","id":"D6DC601C-420A-4D82-913C-6B2D5B9F9D75","subtitle":"Model converged at 14 iterations","createdDate":"2024-08-30T12:50:08Z","title":"Training Completed"}],"evaluationStarted",[{"subtitle":"EmotionsImageClassifier 3","title":"Testing Started","event":"evaluationStarted","id":"E1311B72-C7B3-4562-92BA-1F7396063E2D","createdDate":"2024-08-30T12:50:10Z"}],"evaluationFinished",[{"event":"evaluationFinished","id":"20D797D7-BE11-4E46-BDCF-97C2526CDD53","createdDate":"2024-08-30T12:50:10Z","title":"Testing Completed","subtitle":"EmotionsImageClassifier 3"}],"trainingDataAdded",[{"title":"Training Data Added","event":"trainingDataAdded","subtitle":"Training (3 Labels)","createdDate":"2024-08-30T12:49:52Z","id":"47418DB1-D8E4-4602-B9BF-91F8A26EBFEF"}],"experimentCreated",[{"event":"experimentCreated","subtitle":"EmotionsImageClassifier 3","createdDate":"2024-08-30T12:49:44Z","id":"FCE7B78A-BA7C-491C-A73D-14EFAD2D7C97","title":"Model Source Created"}]],"modelEntity":{"modelURL":"Models\/EmotionsImageClassifier%203.mlmodel","preferredFilename":"","createdDate":"2024-08-30T12:49:44Z","title":"","modifiedDate":"2024-08-30T12:49:44Z","id":"02BAF73E-70E3-4667-A3EB-8C2D6672576C","experimentID":"1A7CC212-3E45-4CEC-A702-D87B5C2DD3BC","version":"1.0"},"createdDate":"2024-08-30T12:49:44Z","validationEntity":{"analysedDataType":"auto","dataResult":{"createdDate":"2024-08-30T12:49:44Z"}},"id":"1A7CC212-3E45-4CEC-A702-D87B5C2DD3BC","settingEntity":{"iterationCount":25,"handActionClassifierAugmentations":[],"handPoseClassifierAugmentations":[],"featureExtractorType":"scenePrintV2","augmentations":["rotate","blur","expose","addNoise","crop","flip"],"harVideoAugmentations":0,"algorithmType":"maxEnt","seedType":"default","taskType":"imageClassifier","featureNames":[],"styleTransferAlgorithmType":"image","transferLearningEmbeddingType":"dynamic"},"evaluationContainerEntity":{"validationEvaluationEntity":{"evaluationResult":{"imageClassifier":{"confusionMatrix":[{"actual":"happy","count":4,"expected":"happy"},{"actual":"happy","count":2,"expected":"neutral"},{"expected":"happy","actual":"neutral","count":1},{"expected":"neutral","actual":"neutral","count":5},{"expected":"neutral","count":1,"actual":"sad"},{"expected":"sad","actual":"sad","count":5}],"statsByLabel":{"sad":{"count":6,"precisionRecall":{"success":{"recall":0.8333333333333334,"precision":1}}},"happy":{"precisionRecall":{"success":{"recall":0.6666666666666666,"precision":0.8}},"count":6},"neutral":{"count":6,"precisionRecall":{"success":{"precision":0.625,"recall":0.8333333333333334}}}},"accuracy":0.7777777777777778}},"dataResult":{"createdDate":"2024-08-30T12:49:44Z"},"analysedDataType":"auto","id":"547c3b5c-f283-4633-816f-bbf4e9b1f6bd","createdDate":"2024-08-30T12:49:44Z"},"testingEvaluationEntity":{"finishTime":"2024-08-30T12:50:10Z","createdDate":"2024-08-30T12:49:44Z","dataSourceID":"A19B28B3-4458-4812-A2CB-665C9A630044","dataResult":{"itemsCount":45,"dataSourceID":"A19B28B3-4458-4812-A2CB-665C9A630044","createdDate":"2024-08-30T12:49:44Z","dataAnalysis":{"issues":[{"severity":"debug","description":"3 classes found, including happy, neutral, sad"},{"severity":"warning","description":"Less than 50 total images found - add more to improve model validation"},{"severity":"debug","description":"Smallest class is \"sad\" with 15 images"},{"severity":"debug","description":"Largest class is \"happy\" with 15 images"}],"summary":{"sampleCount":45,"classCount":3,"canUseValidation":0},"classifierAnalysis":{"labelStats":{"neutral":15,"happy":15,"sad":15}}},"dataURL":"file:\/\/\/Users\/minahanna\/Kodeco\/MMLP\/Create%20ML\/Create%20ML%20SP\/02-Training-Your-Custom-Model-with-Create-ML\/Starter\/Emotions%20Data%20(3%20Labels)\/Testing%20(3%20Labels)\/","classesCount":3},"id":"c4d0362c-8d24-4b54-840b-4697a8ff9a38","startTime":"2024-08-30T12:50:10Z","evaluationResult":{"imageClassifier":{"confusionMatrix":[{"actual":"happy","expected":"happy","count":11},{"expected":"neutral","actual":"happy","count":4},{"expected":"happy","count":1,"actual":"neutral"},{"expected":"neutral","count":11,"actual":"neutral"},{"expected":"sad","actual":"neutral","count":3},{"count":2,"actual":"sad","expected":"happy"},{"expected":"neutral","count":5,"actual":"sad"},{"actual":"sad","count":8,"expected":"sad"}],"accuracy":0.6666666666666666,"statsByLabel":{"sad":{"count":15,"precisionRecall":{"success":{"precision":0.7272727272727273,"recall":0.5333333333333333}}},"happy":{"count":15,"precisionRecall":{"success":{"precision":0.7857142857142857,"recall":0.7333333333333333}}},"neutral":{"precisionRecall":{"success":{"precision":0.55,"recall":0.7333333333333333}},"count":15}},"detail":{"predictions":{"sad":[{"falseNegative":{}},[{"predicted":"happy","url":"file:\/\/\/Users\/minahanna\/Kodeco\/MMLP\/Create%20ML\/Create%20ML%20SP\/02-Training-Your-Custom-Model-with-Create-ML\/Starter\/Emotions%20Data%20(3%20Labels)\/Testing%20(3%20Labels)\/sad\/image0028209.jpg","actual":"sad","predictions":{"happy":0.9999966,"sad":3.3993126e-06,"neutral":3.5299187e-14}},{"url":"file:\/\/\/Users\/minahanna\/Kodeco\/MMLP\/Create%20ML\/Create%20ML%20SP\/02-Training-Your-Custom-Model-with-Create-ML\/Starter\/Emotions%20Data%20(3%20Labels)\/Testing%20(3%20Labels)\/sad\/PrivateTest_84539941.jpg","predicted":"happy","predictions":{"neutral":0.009159979,"happy":0.99083835,"sad":1.6988122e-06},"actual":"sad"},{"predicted":"neutral","predictions":{"happy":5.2652263e-18,"sad":1.2796451e-24,"neutral":1},"url":"file:\/\/\/Users\/minahanna\/Kodeco\/MMLP\/Create%20ML\/Create%20ML%20SP\/02-Training-Your-Custom-Model-with-Create-ML\/Starter\/Emotions%20Data%20(3%20Labels)\/Testing%20(3%20Labels)\/sad\/PrivateTest_44238830.jpg","actual":"sad"},{"actual":"sad","predictions":{"sad":0.018199943,"neutral":0.9818,"happy":2.9414728e-08},"predicted":"neutral","url":"file:\/\/\/Users\/minahanna\/Kodeco\/MMLP\/Create%20ML\/Create%20ML%20SP\/02-Training-Your-Custom-Model-with-Create-ML\/Starter\/Emotions%20Data%20(3%20Labels)\/Testing%20(3%20Labels)\/sad\/image0030185.jpg"},{"url":"file:\/\/\/Users\/minahanna\/Kodeco\/MMLP\/Create%20ML\/Create%20ML%20SP\/02-Training-Your-Custom-Model-with-Create-ML\/Starter\/Emotions%20Data%20(3%20Labels)\/Testing%20(3%20Labels)\/sad\/PrivateTest_50954914.jpg","predicted":"neutral","actual":"sad","predictions":{"happy":1.5601824e-15,"neutral":1,"sad":1.1355176e-21}},{"actual":"sad","predictions":{"happy":4.4865694e-11,"neutral":1,"sad":4.6930035e-19},"url":"file:\/\/\/Users\/minahanna\/Kodeco\/MMLP\/Create%20ML\/Create%20ML%20SP\/02-Training-Your-Custom-Model-with-Create-ML\/Starter\/Emotions%20Data%20(3%20Labels)\/Testing%20(3%20Labels)\/sad\/PrivateTest_68427103.jpg","predicted":"neutral"},{"predictions":{"neutral":1,"happy":1.3748448e-18,"sad":4.273245e-31},"url":"file:\/\/\/Users\/minahanna\/Kodeco\/MMLP\/Create%20ML\/Create%20ML%20SP\/02-Training-Your-Custom-Model-with-Create-ML\/Starter\/Emotions%20Data%20(3%20Labels)\/Testing%20(3%20Labels)\/sad\/PublicTest_34487688.jpg","predicted":"neutral","actual":"sad"}],{"falsePositive":{}},[{"actual":"neutral","predicted":"sad","url":"file:\/\/\/Users\/minahanna\/Kodeco\/MMLP\/Create%20ML\/Create%20ML%20SP\/02-Training-Your-Custom-Model-with-Create-ML\/Starter\/Emotions%20Data%20(3%20Labels)\/Testing%20(3%20Labels)\/neutral\/image0033249.jpg","predictions":{"neutral":0.26911536,"sad":0.7308847,"happy":8.3255e-13}},{"url":"file:\/\/\/Users\/minahanna\/Kodeco\/MMLP\/Create%20ML\/Create%20ML%20SP\/02-Training-Your-Custom-Model-with-Create-ML\/Starter\/Emotions%20Data%20(3%20Labels)\/Testing%20(3%20Labels)\/neutral\/image0014042.jpg","predictions":{"neutral":0.07269953,"happy":5.1666936e-14,"sad":0.92730045},"actual":"neutral","predicted":"sad"},{"predicted":"sad","url":"file:\/\/\/Users\/minahanna\/Kodeco\/MMLP\/Create%20ML\/Create%20ML%20SP\/02-Training-Your-Custom-Model-with-Create-ML\/Starter\/Emotions%20Data%20(3%20Labels)\/Testing%20(3%20Labels)\/neutral\/image0014465.jpg","actual":"neutral","predictions":{"happy":0.081700526,"sad":0.9025067,"neutral":0.015792768}}],{"truePositive":{}},[{"actual":"sad","predicted":"sad","predictions":{"sad":0.9482426,"happy":0.05175739,"neutral":1.0801942e-11},"url":"file:\/\/\/Users\/minahanna\/Kodeco\/MMLP\/Create%20ML\/Create%20ML%20SP\/02-Training-Your-Custom-Model-with-Create-ML\/Starter\/Emotions%20Data%20(3%20Labels)\/Testing%20(3%20Labels)\/sad\/image0029947.jpg"},{"predicted":"sad","actual":"sad","url":"file:\/\/\/Users\/minahanna\/Kodeco\/MMLP\/Create%20ML\/Create%20ML%20SP\/02-Training-Your-Custom-Model-with-Create-ML\/Starter\/Emotions%20Data%20(3%20Labels)\/Testing%20(3%20Labels)\/sad\/image0026046.jpg","predictions":{"happy":0.3443748,"neutral":0.0017109537,"sad":0.6539142}},{"predictions":{"neutral":4.873849e-06,"sad":0.99999464,"happy":4.8326257e-07},"predicted":"sad","url":"file:\/\/\/Users\/minahanna\/Kodeco\/MMLP\/Create%20ML\/Create%20ML%20SP\/02-Training-Your-Custom-Model-with-Create-ML\/Starter\/Emotions%20Data%20(3%20Labels)\/Testing%20(3%20Labels)\/sad\/image0028256.jpg","actual":"sad"},{"predictions":{"sad":0.996133,"neutral":4.640713e-15,"happy":0.0038669568},"predicted":"sad","actual":"sad","url":"file:\/\/\/Users\/minahanna\/Kodeco\/MMLP\/Create%20ML\/Create%20ML%20SP\/02-Training-Your-Custom-Model-with-Create-ML\/Starter\/Emotions%20Data%20(3%20Labels)\/Testing%20(3%20Labels)\/sad\/image0028234.jpg"},{"predictions":{"neutral":1.5228783e-06,"happy":2.4231215e-06,"sad":0.99999607},"url":"file:\/\/\/Users\/minahanna\/Kodeco\/MMLP\/Create%20ML\/Create%20ML%20SP\/02-Training-Your-Custom-Model-with-Create-ML\/Starter\/Emotions%20Data%20(3%20Labels)\/Testing%20(3%20Labels)\/sad\/image0029967.jpg","actual":"sad","predicted":"sad"},{"predicted":"sad","predictions":{"happy":0.31174922,"neutral":0.017904071,"sad":0.6703467},"actual":"sad","url":"file:\/\/\/Users\/minahanna\/Kodeco\/MMLP\/Create%20ML\/Create%20ML%20SP\/02-Training-Your-Custom-Model-with-Create-ML\/Starter\/Emotions%20Data%20(3%20Labels)\/Testing%20(3%20Labels)\/sad\/image0028258.jpg"},{"predictions":{"happy":1.6579262e-10,"sad":1,"neutral":4.5062165e-10},"actual":"sad","predicted":"sad","url":"file:\/\/\/Users\/minahanna\/Kodeco\/MMLP\/Create%20ML\/Create%20ML%20SP\/02-Training-Your-Custom-Model-with-Create-ML\/Starter\/Emotions%20Data%20(3%20Labels)\/Testing%20(3%20Labels)\/sad\/image0028261.jpg"},{"predicted":"sad","actual":"sad","url":"file:\/\/\/Users\/minahanna\/Kodeco\/MMLP\/Create%20ML\/Create%20ML%20SP\/02-Training-Your-Custom-Model-with-Create-ML\/Starter\/Emotions%20Data%20(3%20Labels)\/Testing%20(3%20Labels)\/sad\/image0028263.jpg","predictions":{"happy":2.3995162e-07,"sad":0.95953834,"neutral":0.04046141}}]],"happy":[{"falsePositive":{}},[{"actual":"neutral","url":"file:\/\/\/Users\/minahanna\/Kodeco\/MMLP\/Create%20ML\/Create%20ML%20SP\/02-Training-Your-Custom-Model-with-Create-ML\/Starter\/Emotions%20Data%20(3%20Labels)\/Testing%20(3%20Labels)\/neutral\/PrivateTest_19817034.jpg","predictions":{"happy":0.8542335,"neutral":0.1457664,"sad":8.698243e-08},"predicted":"happy"},{"actual":"sad","url":"file:\/\/\/Users\/minahanna\/Kodeco\/MMLP\/Create%20ML\/Create%20ML%20SP\/02-Training-Your-Custom-Model-with-Create-ML\/Starter\/Emotions%20Data%20(3%20Labels)\/Testing%20(3%20Labels)\/sad\/image0028209.jpg","predicted":"happy","predictions":{"happy":0.9999966,"neutral":3.5299187e-14,"sad":3.3993126e-06}},{"actual":"sad","url":"file:\/\/\/Users\/minahanna\/Kodeco\/MMLP\/Create%20ML\/Create%20ML%20SP\/02-Training-Your-Custom-Model-with-Create-ML\/Starter\/Emotions%20Data%20(3%20Labels)\/Testing%20(3%20Labels)\/sad\/PrivateTest_84539941.jpg","predicted":"happy","predictions":{"sad":1.6988122e-06,"happy":0.99083835,"neutral":0.009159979}}],{"truePositive":{}},[{"predictions":{"sad":4.0637227e-07,"neutral":0.008948728,"happy":0.99105084},"actual":"happy","url":"file:\/\/\/Users\/minahanna\/Kodeco\/MMLP\/Create%20ML\/Create%20ML%20SP\/02-Training-Your-Custom-Model-with-Create-ML\/Starter\/Emotions%20Data%20(3%20Labels)\/Testing%20(3%20Labels)\/happy\/PrivateTest_5142883.jpg","predicted":"happy"},{"predictions":{"happy":0.98834586,"neutral":1.948188e-18,"sad":0.011654131},"actual":"happy","predicted":"happy","url":"file:\/\/\/Users\/minahanna\/Kodeco\/MMLP\/Create%20ML\/Create%20ML%20SP\/02-Training-Your-Custom-Model-with-Create-ML\/Starter\/Emotions%20Data%20(3%20Labels)\/Testing%20(3%20Labels)\/happy\/ffhq_4747.png"},{"predicted":"happy","url":"file:\/\/\/Users\/minahanna\/Kodeco\/MMLP\/Create%20ML\/Create%20ML%20SP\/02-Training-Your-Custom-Model-with-Create-ML\/Starter\/Emotions%20Data%20(3%20Labels)\/Testing%20(3%20Labels)\/happy\/ffhq_4686.png","predictions":{"happy":1,"sad":1.9978867e-16,"neutral":3.1499483e-09},"actual":"happy"},{"predicted":"happy","url":"file:\/\/\/Users\/minahanna\/Kodeco\/MMLP\/Create%20ML\/Create%20ML%20SP\/02-Training-Your-Custom-Model-with-Create-ML\/Starter\/Emotions%20Data%20(3%20Labels)\/Testing%20(3%20Labels)\/happy\/ffhq_4884.png","actual":"happy","predictions":{"happy":0.99999994,"sad":3.788904e-14,"neutral":7.976227e-08}},{"actual":"happy","predictions":{"happy":1,"sad":9.164938e-16,"neutral":4.213574e-12},"predicted":"happy","url":"file:\/\/\/Users\/minahanna\/Kodeco\/MMLP\/Create%20ML\/Create%20ML%20SP\/02-Training-Your-Custom-Model-with-Create-ML\/Starter\/Emotions%20Data%20(3%20Labels)\/Testing%20(3%20Labels)\/happy\/ffhq_4883.png"},{"predictions":{"neutral":9.57561e-19,"happy":1,"sad":2.8466584e-15},"predicted":"happy","actual":"happy","url":"file:\/\/\/Users\/minahanna\/Kodeco\/MMLP\/Create%20ML\/Create%20ML%20SP\/02-Training-Your-Custom-Model-with-Create-ML\/Starter\/Emotions%20Data%20(3%20Labels)\/Testing%20(3%20Labels)\/happy\/ffhq_4698.png"},{"predicted":"happy","url":"file:\/\/\/Users\/minahanna\/Kodeco\/MMLP\/Create%20ML\/Create%20ML%20SP\/02-Training-Your-Custom-Model-with-Create-ML\/Starter\/Emotions%20Data%20(3%20Labels)\/Testing%20(3%20Labels)\/happy\/ffhq_4699.png","actual":"happy","predictions":{"happy":0.9995768,"neutral":1.4726008e-05,"sad":0.0004084594}},{"actual":"happy","predicted":"happy","predictions":{"neutral":1.9619254e-13,"sad":1.389263e-18,"happy":1},"url":"file:\/\/\/Users\/minahanna\/Kodeco\/MMLP\/Create%20ML\/Create%20ML%20SP\/02-Training-Your-Custom-Model-with-Create-ML\/Starter\/Emotions%20Data%20(3%20Labels)\/Testing%20(3%20Labels)\/happy\/ffhq_4842.png"},{"url":"file:\/\/\/Users\/minahanna\/Kodeco\/MMLP\/Create%20ML\/Create%20ML%20SP\/02-Training-Your-Custom-Model-with-Create-ML\/Starter\/Emotions%20Data%20(3%20Labels)\/Testing%20(3%20Labels)\/happy\/ffhq_4945.png","predictions":{"happy":0.9999998,"neutral":4.168469e-14,"sad":1.5675764e-07},"predicted":"happy","actual":"happy"},{"actual":"happy","predicted":"happy","predictions":{"sad":6.270605e-12,"happy":1,"neutral":6.451963e-09},"url":"file:\/\/\/Users\/minahanna\/Kodeco\/MMLP\/Create%20ML\/Create%20ML%20SP\/02-Training-Your-Custom-Model-with-Create-ML\/Starter\/Emotions%20Data%20(3%20Labels)\/Testing%20(3%20Labels)\/happy\/ffhq_4943.png"},{"url":"file:\/\/\/Users\/minahanna\/Kodeco\/MMLP\/Create%20ML\/Create%20ML%20SP\/02-Training-Your-Custom-Model-with-Create-ML\/Starter\/Emotions%20Data%20(3%20Labels)\/Testing%20(3%20Labels)\/happy\/ffhq_4765.png","predictions":{"sad":1.3910133e-05,"happy":0.9999861,"neutral":2.3198498e-15},"predicted":"happy","actual":"happy"}],{"falseNegative":{}},[{"actual":"happy","predictions":{"sad":2.2346804e-17,"happy":3.80509e-05,"neutral":0.999962},"predicted":"neutral","url":"file:\/\/\/Users\/minahanna\/Kodeco\/MMLP\/Create%20ML\/Create%20ML%20SP\/02-Training-Your-Custom-Model-with-Create-ML\/Starter\/Emotions%20Data%20(3%20Labels)\/Testing%20(3%20Labels)\/happy\/PrivateTest_4315069.jpg"},{"predictions":{"sad":1.4539077e-18,"happy":1.23015955e-11,"neutral":1},"predicted":"neutral","url":"file:\/\/\/Users\/minahanna\/Kodeco\/MMLP\/Create%20ML\/Create%20ML%20SP\/02-Training-Your-Custom-Model-with-Create-ML\/Starter\/Emotions%20Data%20(3%20Labels)\/Testing%20(3%20Labels)\/happy\/PrivateTest_25072457.jpg","actual":"happy"},{"actual":"happy","predictions":{"neutral":1,"happy":4.482104e-11,"sad":3.6402613e-25},"predicted":"neutral","url":"file:\/\/\/Users\/minahanna\/Kodeco\/MMLP\/Create%20ML\/Create%20ML%20SP\/02-Training-Your-Custom-Model-with-Create-ML\/Starter\/Emotions%20Data%20(3%20Labels)\/Testing%20(3%20Labels)\/happy\/PrivateTest_14332357.jpg"},{"predictions":{"sad":1.5100019e-08,"neutral":0.99215096,"happy":0.007849035},"url":"file:\/\/\/Users\/minahanna\/Kodeco\/MMLP\/Create%20ML\/Create%20ML%20SP\/02-Training-Your-Custom-Model-with-Create-ML\/Starter\/Emotions%20Data%20(3%20Labels)\/Testing%20(3%20Labels)\/happy\/PrivateTest_9367235.jpg","predicted":"neutral","actual":"happy"}]],"neutral":[{"falsePositive":{}},[{"predicted":"neutral","actual":"happy","predictions":{"sad":2.2346804e-17,"neutral":0.999962,"happy":3.80509e-05},"url":"file:\/\/\/Users\/minahanna\/Kodeco\/MMLP\/Create%20ML\/Create%20ML%20SP\/02-Training-Your-Custom-Model-with-Create-ML\/Starter\/Emotions%20Data%20(3%20Labels)\/Testing%20(3%20Labels)\/happy\/PrivateTest_4315069.jpg"},{"predicted":"neutral","actual":"happy","url":"file:\/\/\/Users\/minahanna\/Kodeco\/MMLP\/Create%20ML\/Create%20ML%20SP\/02-Training-Your-Custom-Model-with-Create-ML\/Starter\/Emotions%20Data%20(3%20Labels)\/Testing%20(3%20Labels)\/happy\/PrivateTest_25072457.jpg","predictions":{"sad":1.4539077e-18,"neutral":1,"happy":1.23015955e-11}},{"predictions":{"neutral":1,"happy":4.482104e-11,"sad":3.6402613e-25},"predicted":"neutral","actual":"happy","url":"file:\/\/\/Users\/minahanna\/Kodeco\/MMLP\/Create%20ML\/Create%20ML%20SP\/02-Training-Your-Custom-Model-with-Create-ML\/Starter\/Emotions%20Data%20(3%20Labels)\/Testing%20(3%20Labels)\/happy\/PrivateTest_14332357.jpg"},{"actual":"happy","predicted":"neutral","predictions":{"happy":0.007849035,"neutral":0.99215096,"sad":1.5100019e-08},"url":"file:\/\/\/Users\/minahanna\/Kodeco\/MMLP\/Create%20ML\/Create%20ML%20SP\/02-Training-Your-Custom-Model-with-Create-ML\/Starter\/Emotions%20Data%20(3%20Labels)\/Testing%20(3%20Labels)\/happy\/PrivateTest_9367235.jpg"},{"actual":"sad","predicted":"neutral","predictions":{"neutral":1,"happy":5.2652263e-18,"sad":1.2796451e-24},"url":"file:\/\/\/Users\/minahanna\/Kodeco\/MMLP\/Create%20ML\/Create%20ML%20SP\/02-Training-Your-Custom-Model-with-Create-ML\/Starter\/Emotions%20Data%20(3%20Labels)\/Testing%20(3%20Labels)\/sad\/PrivateTest_44238830.jpg"},{"actual":"sad","url":"file:\/\/\/Users\/minahanna\/Kodeco\/MMLP\/Create%20ML\/Create%20ML%20SP\/02-Training-Your-Custom-Model-with-Create-ML\/Starter\/Emotions%20Data%20(3%20Labels)\/Testing%20(3%20Labels)\/sad\/image0030185.jpg","predicted":"neutral","predictions":{"neutral":0.9818,"sad":0.018199943,"happy":2.9414728e-08}},{"actual":"sad","predictions":{"happy":1.5601824e-15,"neutral":1,"sad":1.1355176e-21},"url":"file:\/\/\/Users\/minahanna\/Kodeco\/MMLP\/Create%20ML\/Create%20ML%20SP\/02-Training-Your-Custom-Model-with-Create-ML\/Starter\/Emotions%20Data%20(3%20Labels)\/Testing%20(3%20Labels)\/sad\/PrivateTest_50954914.jpg","predicted":"neutral"},{"predicted":"neutral","actual":"sad","predictions":{"happy":4.4865694e-11,"neutral":1,"sad":4.6930035e-19},"url":"file:\/\/\/Users\/minahanna\/Kodeco\/MMLP\/Create%20ML\/Create%20ML%20SP\/02-Training-Your-Custom-Model-with-Create-ML\/Starter\/Emotions%20Data%20(3%20Labels)\/Testing%20(3%20Labels)\/sad\/PrivateTest_68427103.jpg"},{"actual":"sad","predictions":{"sad":4.273245e-31,"neutral":1,"happy":1.3748448e-18},"url":"file:\/\/\/Users\/minahanna\/Kodeco\/MMLP\/Create%20ML\/Create%20ML%20SP\/02-Training-Your-Custom-Model-with-Create-ML\/Starter\/Emotions%20Data%20(3%20Labels)\/Testing%20(3%20Labels)\/sad\/PublicTest_34487688.jpg","predicted":"neutral"}],{"truePositive":{}},[{"predicted":"neutral","url":"file:\/\/\/Users\/minahanna\/Kodeco\/MMLP\/Create%20ML\/Create%20ML%20SP\/02-Training-Your-Custom-Model-with-Create-ML\/Starter\/Emotions%20Data%20(3%20Labels)\/Testing%20(3%20Labels)\/neutral\/PrivateTest_11724564.jpg","actual":"neutral","predictions":{"neutral":0.9999979,"sad":4.8066134e-16,"happy":2.099199e-06}},{"url":"file:\/\/\/Users\/minahanna\/Kodeco\/MMLP\/Create%20ML\/Create%20ML%20SP\/02-Training-Your-Custom-Model-with-Create-ML\/Starter\/Emotions%20Data%20(3%20Labels)\/Testing%20(3%20Labels)\/neutral\/image0030755.jpg","actual":"neutral","predicted":"neutral","predictions":{"neutral":0.99999994,"happy":4.467622e-08,"sad":6.6555045e-14}},{"predictions":{"neutral":0.99991775,"happy":8.2257524e-05,"sad":2.676468e-14},"url":"file:\/\/\/Users\/minahanna\/Kodeco\/MMLP\/Create%20ML\/Create%20ML%20SP\/02-Training-Your-Custom-Model-with-Create-ML\/Starter\/Emotions%20Data%20(3%20Labels)\/Testing%20(3%20Labels)\/neutral\/PrivateTest_22978039.jpg","predicted":"neutral","actual":"neutral"},{"actual":"neutral","predictions":{"sad":9.126741e-14,"neutral":1,"happy":8.1538315e-10},"url":"file:\/\/\/Users\/minahanna\/Kodeco\/MMLP\/Create%20ML\/Create%20ML%20SP\/02-Training-Your-Custom-Model-with-Create-ML\/Starter\/Emotions%20Data%20(3%20Labels)\/Testing%20(3%20Labels)\/neutral\/PrivateTest_11752870.jpg","predicted":"neutral"},{"predictions":{"sad":0.005067409,"happy":0.0021661627,"neutral":0.99276644},"predicted":"neutral","actual":"neutral","url":"file:\/\/\/Users\/minahanna\/Kodeco\/MMLP\/Create%20ML\/Create%20ML%20SP\/02-Training-Your-Custom-Model-with-Create-ML\/Starter\/Emotions%20Data%20(3%20Labels)\/Testing%20(3%20Labels)\/neutral\/image0032248.jpg"},{"predicted":"neutral","predictions":{"happy":6.5821678e-06,"sad":4.881278e-10,"neutral":0.99999344},"actual":"neutral","url":"file:\/\/\/Users\/minahanna\/Kodeco\/MMLP\/Create%20ML\/Create%20ML%20SP\/02-Training-Your-Custom-Model-with-Create-ML\/Starter\/Emotions%20Data%20(3%20Labels)\/Testing%20(3%20Labels)\/neutral\/PrivateTest_16736805.jpg"},{"actual":"neutral","predicted":"neutral","predictions":{"sad":1.8179841e-14,"happy":1.7220808e-17,"neutral":1},"url":"file:\/\/\/Users\/minahanna\/Kodeco\/MMLP\/Create%20ML\/Create%20ML%20SP\/02-Training-Your-Custom-Model-with-Create-ML\/Starter\/Emotions%20Data%20(3%20Labels)\/Testing%20(3%20Labels)\/neutral\/ffhq_5596.png"},{"predicted":"neutral","predictions":{"neutral":1,"happy":3.0183633e-09,"sad":1.9766317e-19},"actual":"neutral","url":"file:\/\/\/Users\/minahanna\/Kodeco\/MMLP\/Create%20ML\/Create%20ML%20SP\/02-Training-Your-Custom-Model-with-Create-ML\/Starter\/Emotions%20Data%20(3%20Labels)\/Testing%20(3%20Labels)\/neutral\/image0021813.jpg"},{"url":"file:\/\/\/Users\/minahanna\/Kodeco\/MMLP\/Create%20ML\/Create%20ML%20SP\/02-Training-Your-Custom-Model-with-Create-ML\/Starter\/Emotions%20Data%20(3%20Labels)\/Testing%20(3%20Labels)\/neutral\/image0016821.jpg","predicted":"neutral","actual":"neutral","predictions":{"sad":7.3948154e-22,"neutral":1,"happy":3.1564323e-18}},{"predicted":"neutral","actual":"neutral","url":"file:\/\/\/Users\/minahanna\/Kodeco\/MMLP\/Create%20ML\/Create%20ML%20SP\/02-Training-Your-Custom-Model-with-Create-ML\/Starter\/Emotions%20Data%20(3%20Labels)\/Testing%20(3%20Labels)\/neutral\/image0014239.jpg","predictions":{"neutral":0.9213872,"sad":0.07861282,"happy":2.2320796e-11}},{"actual":"neutral","predictions":{"neutral":0.9999967,"sad":3.2883759e-06,"happy":5.5644742e-11},"predicted":"neutral","url":"file:\/\/\/Users\/minahanna\/Kodeco\/MMLP\/Create%20ML\/Create%20ML%20SP\/02-Training-Your-Custom-Model-with-Create-ML\/Starter\/Emotions%20Data%20(3%20Labels)\/Testing%20(3%20Labels)\/neutral\/image0021913.jpg"}],{"falseNegative":{}},[{"predictions":{"sad":8.698243e-08,"happy":0.8542335,"neutral":0.1457664},"predicted":"happy","actual":"neutral","url":"file:\/\/\/Users\/minahanna\/Kodeco\/MMLP\/Create%20ML\/Create%20ML%20SP\/02-Training-Your-Custom-Model-with-Create-ML\/Starter\/Emotions%20Data%20(3%20Labels)\/Testing%20(3%20Labels)\/neutral\/PrivateTest_19817034.jpg"},{"predicted":"sad","actual":"neutral","predictions":{"happy":8.3255e-13,"sad":0.7308847,"neutral":0.26911536},"url":"file:\/\/\/Users\/minahanna\/Kodeco\/MMLP\/Create%20ML\/Create%20ML%20SP\/02-Training-Your-Custom-Model-with-Create-ML\/Starter\/Emotions%20Data%20(3%20Labels)\/Testing%20(3%20Labels)\/neutral\/image0033249.jpg"},{"predicted":"sad","actual":"neutral","predictions":{"sad":0.92730045,"neutral":0.07269953,"happy":5.1666936e-14},"url":"file:\/\/\/Users\/minahanna\/Kodeco\/MMLP\/Create%20ML\/Create%20ML%20SP\/02-Training-Your-Custom-Model-with-Create-ML\/Starter\/Emotions%20Data%20(3%20Labels)\/Testing%20(3%20Labels)\/neutral\/image0014042.jpg"},{"url":"file:\/\/\/Users\/minahanna\/Kodeco\/MMLP\/Create%20ML\/Create%20ML%20SP\/02-Training-Your-Custom-Model-with-Create-ML\/Starter\/Emotions%20Data%20(3%20Labels)\/Testing%20(3%20Labels)\/neutral\/image0014465.jpg","actual":"neutral","predicted":"sad","predictions":{"neutral":0.015792768,"sad":0.9025067,"happy":0.081700526}}]]}}}},"accuracy":0.6666666666666666,"analysedDataType":"datasource"},"id":"630d14a3-76a2-4265-8810-abf887efd6b6","evaluationEntities":[],"modifiedDate":"2024-08-30T13:08:35Z","previewType":"imageClassifier","trainingEvaluationEntity":{"dataSourceID":"559AA41B-C4CB-4018-9E90-04BEC5A93EE4","analysedDataType":"none","createdDate":"2024-08-30T12:49:44Z","id":"5bf98255-a446-4499-8fc1-fe365e00599f","dataResult":{"dataURL":"file:\/\/\/Users\/minahanna\/Kodeco\/MMLP\/Create%20ML\/Create%20ML%20SP\/02-Training-Your-Custom-Model-with-Create-ML\/Starter\/Emotions%20Data%20(3%20Labels)\/Training%20(3%20Labels)\/","dataSourceID":"559AA41B-C4CB-4018-9E90-04BEC5A93EE4","dataAnalysis":{"summary":{"classCount":3,"canUseValidation":1,"sampleCount":90},"classifierAnalysis":{"labelStats":{"happy":30,"sad":30,"neutral":30}},"issues":[{"description":"3 classes found, including neutral, sad, happy","severity":"debug"},{"description":"90 images found, automatically creating validation set","severity":"good"},{"description":"Smallest class is \"happy\" with 30 images","severity":"debug"},{"description":"Largest class is \"neutral\" with 30 images","severity":"debug"}]},"itemsCount":90,"createdDate":"2024-08-30T12:49:44Z","classesCount":3},"evaluationResult":{"imageClassifier":{"accuracy":1,"statsByLabel":{"sad":{"count":54,"precisionRecall":{"success":{"recall":1,"precision":1}}},"neutral":{"count":54,"precisionRecall":{"success":{"precision":1,"recall":1}}},"happy":{"precisionRecall":{"success":{"recall":1,"precision":1}},"count":54}},"confusionMatrix":[{"expected":"happy","count":54,"actual":"happy"},{"count":54,"actual":"neutral","expected":"neutral"},{"expected":"sad","actual":"sad","count":54}]}}},"createdDate":"2024-08-30T13:08:35Z"},"contentDataResult":{"createdDate":"2024-08-30T12:49:44Z"},"trainingEntity":{"startTime":"2024-08-30T12:50:06Z","trainingResults":{"imageClassifier":{"confusionMatrix":[{"actual":"happy","expected":"happy","count":54},{"expected":"neutral","actual":"neutral","count":54},{"actual":"sad","count":54,"expected":"sad"}],"statsByLabel":{"happy":{"precisionRecall":{"success":{"precision":1,"recall":1}},"count":54},"sad":{"count":54,"precisionRecall":{"success":{"recall":1,"precision":1}}},"neutral":{"count":54,"precisionRecall":{"success":{"recall":1,"precision":1}}}},"accuracy":1}},"featureExtractionCheckpointMayBeAvailable":false,"snapshottableCheckpoints":{"25":{"modelURL":"file:\/\/\/Users\/minahanna\/Library\/Caches\/com.apple.dt.createml\/projects\/CBFC088B-7330-4866-891E-93D1A17D5EFF2a8efbf3bd2eb2484bb9c8a1603104e807d57abc\/sessions\/checkpoint.sessions\/1A7CC212-3E45-4CEC-A702-D87B5C2DD3BC\/training-000000025.checkpoint.model\/checkpointModel.mlmodel","iteration":25,"createdDate":"2024-08-30T12:50:08Z"}},"dataResult":{"dataAnalysis":{"summary":{"sampleCount":90,"classCount":3,"canUseValidation":1},"issues":[{"severity":"debug","description":"3 classes found, including neutral, sad, happy"},{"severity":"good","description":"90 images found, automatically creating validation set"},{"severity":"debug","description":"Smallest class is \"happy\" with 30 images"},{"severity":"debug","description":"Largest class is \"neutral\" with 30 images"}],"classifierAnalysis":{"labelStats":{"neutral":30,"sad":30,"happy":30}}},"itemsCount":90,"createdDate":"2024-08-30T12:49:44Z","dataSourceID":"559AA41B-C4CB-4018-9E90-04BEC5A93EE4","dataURL":"file:\/\/\/Users\/minahanna\/Kodeco\/MMLP\/Create%20ML\/Create%20ML%20SP\/02-Training-Your-Custom-Model-with-Create-ML\/Starter\/Emotions%20Data%20(3%20Labels)\/Training%20(3%20Labels)\/","classesCount":3},"progress":[{"currentRowIndex":0,"count":0,"tableDone":false,"tableIndex":0,"isLast":false,"percentComplete":0},{"isLast":false,"percentComplete":0,"icTrainingColumnHeader":{"iterationCount":2,"elapsedTime":0.010325074195861816,"hasValidation":true,"validationAccuracy":0.5,"trainingAccuracy":0.6358024691358025},"count":2,"tableDone":false,"currentRowIndex":0,"tableIndex":0},{"isLast":false,"count":3,"tableDone":false,"tableIndex":0,"currentRowIndex":0,"icTrainingColumnHeader":{"hasValidation":true,"elapsedTime":0.012724041938781738,"validationAccuracy":0.5555555555555556,"trainingAccuracy":0.6728395061728395,"iterationCount":3},"percentComplete":0},{"currentRowIndex":0,"percentComplete":0,"icTrainingColumnHeader":{"hasValidation":true,"trainingAccuracy":0.7962962962962963,"validationAccuracy":0.7222222222222222,"elapsedTime":0.02152407169342041,"iterationCount":4},"count":4,"tableDone":false,"tableIndex":0,"isLast":false},{"count":5,"tableDone":false,"currentRowIndex":0,"tableIndex":0,"percentComplete":0,"icTrainingColumnHeader":{"trainingAccuracy":0.8395061728395061,"hasValidation":true,"elapsedTime":0.025943994522094727,"validationAccuracy":0.7777777777777778,"iterationCount":5},"isLast":false},{"isLast":false,"percentComplete":0,"currentRowIndex":0,"tableDone":false,"tableIndex":0,"count":10},{"isLast":false,"tableDone":false,"count":11,"percentComplete":0,"icTrainingColumnHeader":{"elapsedTime":0.048493027687072754,"validationAccuracy":0.7777777777777778,"hasValidation":true,"iterationCount":11,"trainingAccuracy":0.9691358024691358},"currentRowIndex":0,"tableIndex":0},{"isLast":false,"tableIndex":0,"tableDone":true,"percentComplete":0,"currentRowIndex":0,"icTrainingColumnHeader":{"elapsedTime":0.05785810947418213,"iterationCount":14,"trainingAccuracy":1,"hasValidation":true,"validationAccuracy":0.7777777777777778},"count":14},{"count":15,"isLast":false,"tableIndex":0,"tableDone":false,"percentComplete":0,"currentRowIndex":0},{"currentRowIndex":0,"tableDone":false,"percentComplete":0,"tableIndex":0,"count":20,"isLast":false},{"percentComplete":0,"count":25,"tableIndex":0,"currentRowIndex":0,"tableDone":false,"isLast":false},{"currentRowIndex":0,"tableDone":false,"tableIndex":0,"isLast":false,"count":30,"percentComplete":0},{"count":35,"tableIndex":0,"currentRowIndex":0,"isLast":false,"percentComplete":0,"tableDone":false},{"tableIndex":0,"tableDone":false,"count":40,"currentRowIndex":0,"percentComplete":0,"isLast":false},{"tableIndex":0,"currentRowIndex":0,"tableDone":false,"isLast":false,"count":45,"percentComplete":0},{"tableIndex":0,"tableDone":false,"isLast":false,"currentRowIndex":0,"count":50,"percentComplete":0},{"currentRowIndex":0,"isLast":false,"tableIndex":0,"tableDone":false,"count":55,"percentComplete":0},{"tableDone":false,"isLast":false,"count":60,"tableIndex":0,"currentRowIndex":0,"percentComplete":0},{"isLast":false,"currentRowIndex":0,"tableIndex":0,"count":65,"tableDone":false,"percentComplete":0},{"isLast":false,"tableDone":false,"percentComplete":0,"currentRowIndex":0,"count":70,"tableIndex":0},{"isLast":false,"count":75,"percentComplete":0,"tableDone":false,"tableIndex":0,"currentRowIndex":0},{"count":80,"currentRowIndex":0,"percentComplete":0,"isLast":false,"tableIndex":0,"tableDone":false},{"percentComplete":0,"count":85,"tableDone":false,"isLast":false,"currentRowIndex":0,"tableIndex":0},{"count":90,"percentComplete":0,"tableDone":true,"tableIndex":0,"isLast":false,"currentRowIndex":0}],"validationResults":{"imageClassifier":{"accuracy":0.7777777777777778,"statsByLabel":{"happy":{"precisionRecall":{"success":{"recall":0.6666666666666666,"precision":0.8}},"count":6},"neutral":{"count":6,"precisionRecall":{"success":{"precision":0.625,"recall":0.8333333333333334}}},"sad":{"precisionRecall":{"success":{"precision":1,"recall":0.8333333333333334}},"count":6}},"confusionMatrix":[{"expected":"happy","count":4,"actual":"happy"},{"actual":"happy","expected":"neutral","count":2},{"actual":"neutral","expected":"happy","count":1},{"actual":"neutral","count":5,"expected":"neutral"},{"expected":"neutral","count":1,"actual":"sad"},{"count":5,"expected":"sad","actual":"sad"}]}},"dataSourceID":"559AA41B-C4CB-4018-9E90-04BEC5A93EE4","trainingAccuracy":1,"checkpointMetrics":{"25":{"iteration":25,"createdDate":"2024-08-30T12:50:08Z","metrics":{}}},"validationAccuracy":0.7777777777777778,"snapshottableCheckpointModelURL":"Checkpoints\/1A7CC212-3E45-4CEC-A702-D87B5C2DD3BC.EmotionsImageClassifier3.checkpoint\/training-000000025.checkpoint.model\/checkpointModel.mlmodel","finishTime":"2024-08-30T12:50:08Z","analysedDataType":"datasource","resumableCheckpoint":{"checkpointURL":"file:\/\/\/Users\/minahanna\/Library\/Caches\/com.apple.dt.createml\/projects\/CBFC088B-7330-4866-891E-93D1A17D5EFF2a8efbf3bd2eb2484bb9c8a1603104e807d57abc\/sessions\/checkpoint.sessions\/1A7CC212-3E45-4CEC-A702-D87B5C2DD3BC\/training-000000025.checkpoint","iteration":25,"createdDate":"2024-08-30T12:50:08Z"},"resumableCheckpointURL":"Checkpoints\/1A7CC212-3E45-4CEC-A702-D87B5C2DD3BC.EmotionsImageClassifier3.checkpoint"}}